ha_enviro_plus/__init__.py
ha_enviro_plus/agent.py
ha_enviro_plus/sensors.py
ha_enviro_plus/settings.py
ha_enviro_plus-0.1.1.dist-info/licenses/LICENSE
tests/__init__.py
tests/conftest.py
tests/hardware/__init__.py
tests/hardware/test_hardware_sensors.py
tests/integration/__init__.py
tests/integration/test_end_to_end.py
tests/integration/test_mqtt_integration.py
tests/unit/__init__.py
tests/unit/test_agent.py
tests/unit/test_sensors.py
tests/unit/test_settings.py
ha_enviro_plus-0.1.1.dist-info/METADATA
ha_enviro_plus-0.1.1.dist-info/WHEEL
ha_enviro_plus-0.1.1.dist-info/entry_points.txt
ha_enviro_plus-0.1.1.dist-info/top_level.txt
ha_enviro_plus-0.1.1.dist-info/RECORD
