Metadata-Version: 2.4
Name: ha-enviro-plus
Version: 0.1.1
Summary: Enviro+ to Home Assistant MQTT Agent
Author: Jeff Luckett
License: MIT
Keywords: homeassistant,mqtt,enviro,raspberry-pi,sensors
Requires-Python: >=3.9
License-File: LICENSE
Requires-Dist: enviroplus
Requires-Dist: paho-mqtt>=2.0
Requires-Dist: psutil
Provides-Extra: dev
Requires-Dist: pytest>=7.4.0; extra == "dev"
Requires-Dist: pytest-cov>=4.1.0; extra == "dev"
Requires-Dist: pytest-mock>=3.11.0; extra == "dev"
Requires-Dist: pytest-asyncio>=0.21.0; extra == "dev"
Requires-Dist: pytest-timeout>=2.1.0; extra == "dev"
Requires-Dist: black>=23.0.0; extra == "dev"
Requires-Dist: flake8>=6.0.0; extra == "dev"
Requires-Dist: mypy>=1.5.0; extra == "dev"
Dynamic: license-file
Dynamic: requires-python
